Workbook

Sheet Pricing
A1: INTERNAL — Shared National Talent: monthly price per assignment | الكوادر الوطنية المشتركة — السعر الشهري لكل إسناد (داخلي)
A2: Role | B2: Human resources | C2: الوظيفة | D2: Choose from the list
A3: Monthly salary, all-inclusive (SAR) — minimum 6,000 | B3: 6000 | C3: الراتب الشهري شاملاً البدلات (ريال) — الحد الأدنى 6,000 | D3: Includes transport, housing and commissions
A4: Share of a full-time month assigned to this client (%) | B4: 50 | C4: نسبة الشهر الكامل المسندة لهذا العميل (%) | D4: Or enter the hours below
A5: Hours per month for this client (optional, overrides the share) | C5: ساعات هذا العميل شهرياً (اختياري، يغلب النسبة) | D5: Leave empty to use the share
A6: Hours in a full-time month | B6: =5*8*52/12 | C6: ساعات الشهر الكامل | D6: 5 days × 8 hours × 52 ÷ 12 = 173.33 — owner decision
A7: Contract term in months | B7: 12 | C7: مدة العقد بالأشهر
A8: Employer social insurance rate (%) | B8: 11.75 | C8: نسبة التأمينات الاجتماعية على صاحب العمل (%) | D8: Saudi employer share — assumption to confirm with GOSI
A9: Medical insurance per year per employee (SAR) | B9: 600 | C9: التأمين الطبي سنوياً لكل موظف (ريال) | D9: Current assumption — replace with the insurer quote
A10: Field travel allowance per month, full-time (SAR) — non-administrative roles | B10: 0 | C10: بدل التنقل الميداني شهرياً دوام كامل (ريال) — للوظائف غير الإدارية | D10: Enter the amount for field roles
A11: Our fee on top of all costs (%) | B11: 15 | C11: نسبتنا فوق كل التكاليف (%) | D11: Owner decision 2026-10-22
A13: Full-time monthly cost of the employee | C13: التكلفة الشهرية للموظف بدوام كامل
A14: Salary, all-inclusive | B14: =B3 | C14: الراتب شاملاً البدلات
A15: Employer social insurance | B15: =B3*B8/100 | C15: التأمينات الاجتماعية على صاحب العمل | D15: Salary × rate
A16: Medical insurance | B16: =B9/12 | C16: التأمين الطبي | D16: Annual ÷ 12
A17: End of service accrual | B17: =B3/24 | C17: مكافأة نهاية الخدمة | D17: Salary ÷ 24 (half a month a year for five years)
A18: Leave pay (21 days a year) | B18: =B3/30*21/12 | C18: بدل الإجازة (21 يوماً) | D18: Salary ÷ 30 × 21 ÷ 12
A19: Field travel allowance | B19: =IF(B2="Field / non-administrative",B10,0) | C19: بدل التنقل الميداني | D19: Only for field roles
A20: Total full-time cost per month | B20: =SUM(B14:B19) | C20: إجمالي التكلفة الشهرية بدوام كامل
A22: This client assignment | C22: إسناد هذا العميل
A23: Share of a full-time month applied | B23: =IF(ISNUMBER(B5),MIN(1,B5/B6),B4/100) | C23: النسبة المطبقة من الشهر الكامل
A24: Cost of this assignment per month | B24: =B20*B23 | C24: تكلفة هذا الإسناد شهرياً
A25: Our fee | B25: =B24*B11/100 | C25: رسمنا | D25: Cost × fee %
A26: Monthly price excl. VAT | B26: =MROUND(B24+B25,10) | C26: السعر الشهري قبل الضريبة | D26: Rounded to the nearest 10
A27: VAT 15% | B27: =B26*0.15 | C27: ضريبة القيمة المضافة 15%
A28: Monthly price incl. VAT | B28: =B26+B27 | C28: السعر الشهري شامل الضريبة
A29: Total for the term excl. VAT | B29: =B26*B7 | C29: الإجمالي للمدة قبل الضريبة
A30: Counts in Nitaqat for the client (indicative) | B30: =IF(B23>=0.99,"1 Saudi",IF(B23>0,"0.5 Saudi if a real part-time contract is registered","—")) | C30: الاحتساب في نطاقات للعميل (استرشادي) | D30: Depends on the legal structure — to be confirmed

Sheet Rate card
A1: INTERNAL — Rate card: hourly price of a Saudi employee by role and utilisation | بطاقة الأسعار: سعر ساعة الموظف السعودي بحسب الوظيفة ونسبة الإشغال
A3: Hours in a full-time month (days per week × hours per day × 52 ÷ 12) | B3: =E3*E4*52/12 | D3: Working days per week | E3: 5
A4: Employer social insurance rate on basic + housing (%) | B4: 11.75 | D4: Hours per day | E4: 8
A5: Medical insurance per year (SAR) | B5: 600 | D5: Expected variable-pay achievement (%) | E5: 100
A6: Our fee on top of all costs (%) | B6: 15
A7: Expected billable utilisation if not stated per role (%) | B7: 70
A8: Mandatory development hours per month, not billable (training, courses, mentoring) — placeholder to confirm | B8: 8
A9: Training and development budget per year per employee (SAR) — placeholder to confirm | B9: 3000
A11: Role | B11: Job nature | C11: Guaranteed package per month (SAR) = higher of 6,000 and the Ministry minimum | D11: Basic % | E11: Housing % | F11: Transport and other % | G11: Variable pay target at 100% KPI per month (SAR) | H11: Field travel allowance per month (SAR) | I11: Billable utilisation % | J11: Full-time monthly cost incl. training | K11: Billable hours per month (after development hours) | L11: Cost per hour | M11: Rate per hour excl. VAT | N11: Actual utilisation at which revenue only covers cost % | O11: Ministry minimum Saudi salary for the profession (SAR)
A12: Human resources | B12: Fixed + efficiency KPI | C12: =MAX(6000,O12) | D12: 60 | E12: 25 | F12: 15 | G12: 0 | H12: 0 | I12: 70 | J12: =C12+(C12*(D12+E12)/100*$B$4/100)+$B$5/12+C12/24+C12/30*21/12+G12*$E$5/100+H12+$B$9/12 | K12: =MAX(0,$B$3-$B$8)*I12/100 | L12: =J12/K12 | M12: =MROUND(L12*(1+$B$6/100),1) | N12: =I12/(1+$B$6/100) | O12: 0
A13: Accounting | B13: Administrative | C13: =MAX(6000,O13) | D13: 60 | E13: 25 | F13: 15 | G13: 0 | H13: 0 | I13: 70 | J13: =C13+(C13*(D13+E13)/100*$B$4/100)+$B$5/12+C13/24+C13/30*21/12+G13*$E$5/100+H13+$B$9/12 | K13: =MAX(0,$B$3-$B$8)*I13/100 | L13: =J13/K13 | M13: =MROUND(L13*(1+$B$6/100),1) | N13: =I13/(1+$B$6/100) | O13: 6000
A14: Marketing | B14: Fixed + KPI | C14: =MAX(6000,O14) | D14: 60 | E14: 25 | F14: 15 | G14: 0 | H14: 0 | I14: 70 | J14: =C14+(C14*(D14+E14)/100*$B$4/100)+$B$5/12+C14/24+C14/30*21/12+G14*$E$5/100+H14+$B$9/12 | K14: =MAX(0,$B$3-$B$8)*I14/100 | L14: =J14/K14 | M14: =MROUND(L14*(1+$B$6/100),1) | N14: =I14/(1+$B$6/100) | O14: 5500
A15: Sales | B15: Fixed + commission on sales growth | C15: =MAX(6000,O15) | D15: 60 | E15: 25 | F15: 15 | G15: 0 | H15: 0 | I15: 70 | J15: =C15+(C15*(D15+E15)/100*$B$4/100)+$B$5/12+C15/24+C15/30*21/12+G15*$E$5/100+H15+$B$9/12 | K15: =MAX(0,$B$3-$B$8)*I15/100 | L15: =J15/K15 | M15: =MROUND(L15*(1+$B$6/100),1) | N15: =I15/(1+$B$6/100) | O15: 0
A16: Purchasing | B16: Fixed + savings and negotiation | C16: =MAX(6000,O16) | D16: 60 | E16: 25 | F16: 15 | G16: 0 | H16: 0 | I16: 70 | J16: =C16+(C16*(D16+E16)/100*$B$4/100)+$B$5/12+C16/24+C16/30*21/12+G16*$E$5/100+H16+$B$9/12 | K16: =MAX(0,$B$3-$B$8)*I16/100 | L16: =J16/K16 | M16: =MROUND(L16*(1+$B$6/100),1) | N16: =I16/(1+$B$6/100) | O16: 0
A17: Administrative support | B17: Administrative | C17: =MAX(6000,O17) | D17: 60 | E17: 25 | F17: 15 | G17: 0 | H17: 0 | I17: 70 | J17: =C17+(C17*(D17+E17)/100*$B$4/100)+$B$5/12+C17/24+C17/30*21/12+G17*$E$5/100+H17+$B$9/12 | K17: =MAX(0,$B$3-$B$8)*I17/100 | L17: =J17/K17 | M17: =MROUND(L17*(1+$B$6/100),1) | N17: =I17/(1+$B$6/100) | O17: 0
A18: Field / non-administrative | B18: Field | C18: =MAX(6000,O18) | D18: 60 | E18: 25 | F18: 15 | G18: 0 | H18: 0 | I18: 70 | J18: =C18+(C18*(D18+E18)/100*$B$4/100)+$B$5/12+C18/24+C18/30*21/12+G18*$E$5/100+H18+$B$9/12 | K18: =MAX(0,$B$3-$B$8)*I18/100 | L18: =J18/K18 | M18: =MROUND(L18*(1+$B$6/100),1) | N18: =I18/(1+$B$6/100) | O18: 0
A19: Engineering | B19: Fixed + project KPI | C19: =MAX(6000,O19) | D19: 60 | E19: 25 | F19: 15 | G19: 0 | H19: 0 | I19: 70 | J19: =C19+(C19*(D19+E19)/100*$B$4/100)+$B$5/12+C19/24+C19/30*21/12+G19*$E$5/100+H19+$B$9/12 | K19: =MAX(0,$B$3-$B$8)*I19/100 | L19: =J19/K19 | M19: =MROUND(L19*(1+$B$6/100),1) | N19: =I19/(1+$B$6/100) | O19: 8000
A20: Project management | B20: Fixed + milestones | C20: =MAX(6000,O20) | D20: 60 | E20: 25 | F20: 15 | G20: 0 | H20: 0 | I20: 70 | J20: =C20+(C20*(D20+E20)/100*$B$4/100)+$B$5/12+C20/24+C20/30*21/12+G20*$E$5/100+H20+$B$9/12 | K20: =MAX(0,$B$3-$B$8)*I20/100 | L20: =J20/K20 | M20: =MROUND(L20*(1+$B$6/100),1) | N20: =I20/(1+$B$6/100) | O20: 6000
A22: How the rate is built
A23: Full-time monthly cost = guaranteed package + employer social insurance on basic and housing + medical + end of service (package ÷ 24) + leave pay (21 days) + variable pay target + field travel allowance + training budget ÷ 12.
A24: Billable hours = (hours in a full-time month − development hours) × billable utilisation. Cost per hour = full-time cost ÷ productive hours. Rate per hour = cost per hour + our fee.
A25: Lower utilisation means fewer billable hours to carry the same cost, so the hourly rate rises. If the real utilisation falls to the last column, revenue only covers cost: that is the floor to watch.
A26: Training: every employee has mandatory development hours each month and a yearly training budget; both are inside the rate, so the client buys a Saudi employee who is being trained, certified and prepared for the market, not only hours.
A27: Package: 20 hours, 40 hours and 80 hours a month are shown on the sheet "Hour packages".
A28: Guaranteed package = the higher of SAR 6,000 and the Ministry minimum Saudi salary for the profession (column O). Variable pay is on top of the package, never inside it: sales growth for sales, lower cost and better negotiation for purchasing, operational efficiency for human resources, and the KPI of each role.

Sheet Hour packages
A1: INTERNAL — Monthly price by hours assigned | السعر الشهري بحسب الساعات المسندة
A3: Role | B3: Rate per hour | C3: 20 hours | D3: 40 hours | E3: 80 hours | F3: 120 hours | G3: Full-time price (173.33 h at 100%) | H3: Hours at which a package equals the full-time cost
A4: ='Rate card'!A12 | B4: ='Rate card'!M12 | C4: =B4*20 | D4: =B4*40 | E4: =B4*80 | F4: =B4*120 | G4: =MROUND('Rate card'!J12*(1+'Rate card'!$B$6/100),10) | H4: =G4/B4
A5: ='Rate card'!A13 | B5: ='Rate card'!M13 | C5: =B5*20 | D5: =B5*40 | E5: =B5*80 | F5: =B5*120 | G5: =MROUND('Rate card'!J13*(1+'Rate card'!$B$6/100),10) | H5: =G5/B5
A6: ='Rate card'!A14 | B6: ='Rate card'!M14 | C6: =B6*20 | D6: =B6*40 | E6: =B6*80 | F6: =B6*120 | G6: =MROUND('Rate card'!J14*(1+'Rate card'!$B$6/100),10) | H6: =G6/B6
A7: ='Rate card'!A15 | B7: ='Rate card'!M15 | C7: =B7*20 | D7: =B7*40 | E7: =B7*80 | F7: =B7*120 | G7: =MROUND('Rate card'!J15*(1+'Rate card'!$B$6/100),10) | H7: =G7/B7
A8: ='Rate card'!A16 | B8: ='Rate card'!M16 | C8: =B8*20 | D8: =B8*40 | E8: =B8*80 | F8: =B8*120 | G8: =MROUND('Rate card'!J16*(1+'Rate card'!$B$6/100),10) | H8: =G8/B8
A9: ='Rate card'!A17 | B9: ='Rate card'!M17 | C9: =B9*20 | D9: =B9*40 | E9: =B9*80 | F9: =B9*120 | G9: =MROUND('Rate card'!J17*(1+'Rate card'!$B$6/100),10) | H9: =G9/B9
A10: ='Rate card'!A18 | B10: ='Rate card'!M18 | C10: =B10*20 | D10: =B10*40 | E10: =B10*80 | F10: =B10*120 | G10: =MROUND('Rate card'!J18*(1+'Rate card'!$B$6/100),10) | H10: =G10/B10
A11: ='Rate card'!A19 | B11: ='Rate card'!M19 | C11: =B11*20 | D11: =B11*40 | E11: =B11*80 | F11: =B11*120 | G11: =MROUND('Rate card'!J19*(1+'Rate card'!$B$6/100),10) | H11: =G11/B11
A12: ='Rate card'!A20 | B12: ='Rate card'!M20 | C12: =B12*20 | D12: =B12*40 | E12: =B12*80 | F12: =B12*120 | G12: =MROUND('Rate card'!J20*(1+'Rate card'!$B$6/100),10) | H12: =G12/B12
A14: Prices exclude VAT (15%). The rate per hour comes from the "Rate card" sheet and moves with the utilisation target of each role.

Sheet Pay structure
A1: INTERNAL — Pay structure by nature of work | هيكل الراتب بحسب طبيعة العمل
A3: Job nature | B3: Fixed part (guaranteed) | C3: Allowances | D3: Variable part | E3: Performance measure (KPI) | F3: Notes
A4: Administrative (HR, accounting, administrative support) | B4: Basic salary + housing | C4: Transport | D4: None, or a quarterly bonus | E4: Timely delivery, accuracy, client satisfaction | F4: Fixed package; the hourly rate carries the cost.
A5: Human resources | B5: Basic salary + housing | C5: Transport | D5: Variable pay on top of the guaranteed package | E5: Operational efficiency of the client staff (turnover, time to hire, compliance) | F5: Variable pay is on top, not inside the guaranteed package.
A6: Marketing | B6: Basic salary + housing | C6: Transport | D6: Variable pay on top | E6: Campaign results and leads | F6: Variable pay is on top of the guaranteed package.
A7: Purchasing | B7: Basic salary + housing | C7: Transport | D7: Variable pay on top | E7: Reduction of purchase cost, negotiation savings, supplier performance | F7: Variable pay is on top of the guaranteed package.
A8: Sales | B8: Basic salary + housing (guaranteed ≥ 6,000 all-inclusive) | C8: Transport | D8: Commission on closed contracts | E8: Growth in sales volume: contracts closed and collected revenue | F8: Commission is on top of the guaranteed package; its expected value is included in the hourly rate (column G of the Rate card).
A9: Field (non-administrative) | B9: Basic salary + housing | C9: Transport + field travel allowance | D9: Optional | E9: Visits completed, report quality | F9: Field travel allowance is charged only for field roles.
A10: Rules that do not change: the guaranteed package is at least SAR 6,000 all-inclusive; every employee has a real contract, real work and registered social insurance; variable pay is never a substitute for the guaranteed package. | B10: Basic salary + housing | C10: Transport | D10: Milestone payment | E10: Milestones delivered on time and on scope | F10: Price by project with a fixed scope; the milestone payment is part of the project price.

Sheet Development plan
A1: INTERNAL — Development plan for every Saudi employee | خطة التطوير لكل موظف سعودي
A3: Component | B3: What it is | C3: When | D3: Evidence kept | E3: Counts toward the monthly development hours
A4: Onboarding and role standards | B4: Real job description, tools, client rules, confidentiality | C4: First month | D4: Signed job description | E4: Yes
A5: Professional courses | B5: Courses and certificates matched to the role; accredited where the Ministry guide requires it (for example SOCPA for accounting) | C5: Every quarter, mandatory | D5: Certificate or attendance record | E5: Yes
A6: Mentoring and supervision | B6: Weekly review with a senior manager, feedback on real deliverables | C6: Weekly | D6: Review notes | E6: Yes
A7: Performance review | B7: KPIs by job nature (see Pay structure), reviewed monthly and quarterly | C7: Monthly and quarterly | D7: Scorecard | E7: Yes
A8: Market readiness | B8: CV, interview skills, portfolio of delivered work, introductions to employers | C8: Ongoing | D8: Portfolio file | E8: Yes
A9: Empowerment path (phase 2, postponed) | B9: Support to build ventures and introductions to incubators and funds | C9: Later | D9: Decision of the owner | E9: —
A11: Integrity rules: every assignment has real work with a client deliverable, a timesheet and a signed scope; no employee is registered without actual work; training and work records are kept for each employee and can be shown to the Ministry.

Sheet Utilisation
A1: Client / assignment | B1: Share of month % | C1: Price excl. VAT | D1: Cost | E1: Our fee
C2: =IF(B2="","",MROUND(Pricing!$B$20*B2/100*(1+Pricing!$B$11/100),10)) | D2: =IF(B2="","",Pricing!$B$20*B2/100) | E2: =IF(B2="","",C2-D2)
C3: =IF(B3="","",MROUND(Pricing!$B$20*B3/100*(1+Pricing!$B$11/100),10)) | D3: =IF(B3="","",Pricing!$B$20*B3/100) | E3: =IF(B3="","",C3-D3)
C4: =IF(B4="","",MROUND(Pricing!$B$20*B4/100*(1+Pricing!$B$11/100),10)) | D4: =IF(B4="","",Pricing!$B$20*B4/100) | E4: =IF(B4="","",C4-D4)
C5: =IF(B5="","",MROUND(Pricing!$B$20*B5/100*(1+Pricing!$B$11/100),10)) | D5: =IF(B5="","",Pricing!$B$20*B5/100) | E5: =IF(B5="","",C5-D5)
C6: =IF(B6="","",MROUND(Pricing!$B$20*B6/100*(1+Pricing!$B$11/100),10)) | D6: =IF(B6="","",Pricing!$B$20*B6/100) | E6: =IF(B6="","",C6-D6)
C7: =IF(B7="","",MROUND(Pricing!$B$20*B7/100*(1+Pricing!$B$11/100),10)) | D7: =IF(B7="","",Pricing!$B$20*B7/100) | E7: =IF(B7="","",C7-D7)
A9: Total | B9: =SUM(B2:B7) | C9: =SUM(C2:C7) | D9: =SUM(D2:D7) | E9: =SUM(E2:E7)
A10: Unused capacity (cost we carry) | B10: =MAX(0,100-B9) | D10: =Pricing!B20*B10/100
A11: Result vs full-time cost | C11: =C9-Pricing!B20
A13: Fill the clients and their shares for one employee. If the shares total less than 100% the unused part is our cost; above 100% is not allowed.
